django_xor_formfields-0.1.0.dist-info/top_level.txt
django_xor_formfields-0.1.0.dist-info/DESCRIPTION.rst
django_xor_formfields-0.1.0.dist-info/RECORD
django_xor_formfields-0.1.0.dist-info/METADATA
django_xor_formfields-0.1.0.dist-info/WHEEL
django_xor_formfields-0.1.0.dist-info/metadata.json
xorformfields/test_settings.py
xorformfields/tests.py
xorformfields/__init__.py
xorformfields/models.py
xorformfields/static/mutually_exclusive_widget.js
xorformfields/forms/widgets.py
xorformfields/forms/__init__.py
xorformfields/forms/fields.py
