Metadata-Version: 2.0
Name: django-xor-formfields
Version: 0.1.0
Summary: Mutually Exclusive form field wigets for Django
Home-page: https://github.com/dschep/django-mutuallyexclusive-formfields
Author: Daniel Schep
Author-email: dschep@gmail.com
License: MIT
Keywords: django development forms
Platform: UNKNOWN
Classifier: Development Status :: 4 - Beta
Classifier: Intended Audience :: Developers
Classifier: License :: OSI Approved :: MIT License
Classifier: Programming Language :: Python :: 2
Classifier: Programming Language :: Python :: 2.6
Classifier: Programming Language :: Python :: 2.7
Classifier: Programming Language :: Python :: 3
Classifier: Programming Language :: Python :: 3.0
Classifier: Programming Language :: Python :: 3.1
Classifier: Programming Language :: Python :: 3.2
Classifier: Programming Language :: Python :: 3.3
Classifier: Programming Language :: Python :: 3.4
Requires-Dist: django
Requires-Dist: requests
